{
  "project_info": {
    "project_number": "105070098064",
    "project_id": "e-school-7ad71",
    "storage_bucket": "e-school-7ad71.appspot.com"
  },
  "client": [
    {
      "client_info": {
        "mobilesdk_app_id": "1:105070098064:android:5bd815ce8cedbe7735ca15",
        "android_client_info": {
          "package_name": "com.wrteam.eschool"
        }
      },
      "oauth_client": [],
      "api_key": [
        {
          "current_key": "AIzaSyAiTRz3aF3DKsKjVBRVR81SMX_goQk1svs"
        }
      ],
      "services": {
        "appinvite_service": {
          "other_platform_oauth_client": []
        }
      }
    },
    {
      "client_info": {
        "mobilesdk_app_id": "1:105070098064:android:4aba3dc00737575b35ca15",
        "android_client_info": {
          "package_name": "com.wrteam.eschool.teacher"
        }
      },
      "oauth_client": [],
      "api_key": [
        {
          "current_key": "AIzaSyAiTRz3aF3DKsKjVBRVR81SMX_goQk1svs"
        }
      ],
      "services": {
        "appinvite_service": {
          "other_platform_oauth_client": []
        }
      }
    }
  ],
  "configuration_version": "1"
}